offline_voice_assistant-1.0.0.dist-info/licenses/LICENSE
voiceassistant/__init__.py
voiceassistant/__main__.py
offline_voice_assistant-1.0.0.dist-info/METADATA
offline_voice_assistant-1.0.0.dist-info/WHEEL
offline_voice_assistant-1.0.0.dist-info/top_level.txt
offline_voice_assistant-1.0.0.dist-info/RECORD
